{
  "project_info": {
    "project_number": "571073838031",
    "project_id": "credit-vault-dc626",
    "storage_bucket": "credit-vault-dc626.firebasestorage.app"
  },
  "client": [
    {
      "client_info": {
        "mobilesdk_app_id": "1:571073838031:android:5b4d8098c7e7caaf2eb0ba",
        "android_client_info": {
          "package_name": "com.credit.creditvault"
        }
      },
      "oauth_client": [],
      "api_key": [
        {
          "current_key": "AIzaSyDjPfQlMJHHQPN_BQHnw-Cf56I_EZ7YORo"
        }
      ],
      "services": {
        "appinvite_service": {
          "other_platform_oauth_client": []
        }
      }
    }
  ],
  "configuration_version": "1"
}